qoqo_qasm-0.15.3.dist-info/METADATA
qoqo_qasm-0.15.3.dist-info/WHEEL
qoqo_qasm-0.15.3.dist-info/licenses/LICENSE
qoqo_qasm/DEPENDENCIES
qoqo_qasm/__init__.py
qoqo_qasm/qoqo_qasm.cpython-313-darwin.so
qoqo_qasm-0.15.3.dist-info/RECORD
