Metadata-Version: 2.4
Name: qoqo_qasm
Version: 0.15.3
Requires-Dist: qoqo>=1.21
Requires-Dist: qoqo-calculator-pyo3>=1.7
Requires-Dist: tomli ; extra == 'docs'
Requires-Dist: numpy ; extra == 'docs'
Requires-Dist: sphinx>=2.1 ; extra == 'docs'
Requires-Dist: nbsphinx ; extra == 'docs'
Requires-Dist: pygments ; extra == 'docs'
Requires-Dist: recommonmark ; extra == 'docs'
Requires-Dist: myst-parser ; extra == 'docs'
Requires-Dist: sphinx-rtd-theme ; extra == 'docs'
Provides-Extra: docs
License-File: LICENSE
Home-Page: https://github.com/HQSquantumsimulations/qoqo_qasm
Maintainer-email: HQS Quantum Simulations GmbH <info@quantumsimulations.de>
License: Apache-2.0 AND Apache-2.0 with LLVM-exception AND MIT AND Unicode-DFS-2016 AND
Requires-Python: >=3.10
